Workbook

Sheet LEAME
A1: CS-10 — Seguimiento de inscripciones e ingresos
A3: Clasificación | B3: RESTRINGIDO — identidad, datos comerciales y pagos
A4: Versión | B4: 0.3 — plantilla operativa
A5: Propietario | B5: Coordinación de ronda
A6: Uso | B6: Registrar una fila por organización/ronda. No almacenar resultados técnicos.
A7: Confirmación | B7: Solo procede con CS-09 aprobado y pago u orden aceptada.
A8: Capacidad | B8: Individual: máximo 4 analizadores por bloque. CO/SO₂ simultáneo: máximo 3 organizaciones y 6 analizadores.
A9: Comunicaciones | B9: Solo calaire_med@unal.edu.co o carpeta institucional controlada.
A10: Protección | B10: Clave inicial: CAMBIAR-CS10. Debe cambiarla la coordinación antes del uso real. La protección de hoja no sustituye el control de acceso institucional.
A11: Retención | B11: 5 años, conforme al control documental aplicable.

Sheet Tracker
A1: ID del cliente potencial/cliente | B1: Organización | C1: País | D1: Idioma preferido | E1: ID de ronda | F1: Analizadores de CO | G1: Analizadores de SO₂ | H1: Analizadores de O₃ | I1: Analizadores de NO/NO₂ | J1: Cantidad de analizadores | K1: Número de cotización | L1: Revisión de cotización | M1: Valor cotizado (COP) | N1: Valor comprometido actual (COP) | O1: Vencimiento de cotización | P1: Fecha límite de aceptación | Q1: Fecha límite de pago/orden de compra | R1: Fecha de inscripción | S1: Fecha y hora de aceptación | T1: Canal de aceptación | U1: Laboratorio acreditado | V1: Elegibilidad completa | W1: Estado de revisión del contrato | X1: Fecha de revisión del contrato | Y1: Revisor del contrato | Z1: Estado de orden/pago/factura | AA1: Valor recibido (COP) | AB1: Saldo pendiente (COP) | AC1: % pagado | AD1: Vencimiento de próxima cuota | AE1: Número de factura | AF1: Código de participante | AG1: Configuración operativa | AH1: Estado comercial | AI1: Grupo de lista de espera | AJ1: Fecha y hora de lista de espera | AK1: Posición en lista de espera | AL1: Último cupo disponible | AM1: Alerta de capacidad | AN1: Alerta de pago | AO1: Estado de cancelación/reembolso | AP1: Fecha de cancelación | AQ1: Referencia de reembolso/nota crédito | AR1: Exposición cambiaria | AS1: Responsable | AT1: Próxima acción | AU1: Enlace/ubicación de comunicación | AV1: Fecha de expresión de interés | AW1: Vencimiento de expresión de interés | AX1: Indicador de interés obsoleto | AY1: Consentimiento de mercadeo | AZ1: Referencia CS-09 | BA1: Referencia CS-12 | BB1: Notas
J2: =SUM(F2:I2) -> 0 | AB2: =IF(N2="","",MAX(0,N2-AA2)) | AC2: =IF(N2="","",IF(N2=0,0,AA2/N2)) | AI2: =IF(A2="","",IF(V2="Yes",IF(U2="Yes",1,2),"")) | AK2: =IF(A2="","",IF(AJ2="","",COUNTIFS($E$2:$E$201,E2,$AI$2:$AI$201,AI2,$AJ$2:$AJ$201,"<="&AJ2))) | AL2: =IF(A2="","",IF(AH2<>"Confirmado","No",IF(AG2="CO/SO₂ simultáneos",IF(OR(COUNTIFS($E$2:$E$201,E2,$AH$2:$AH$201,"Confirmado",$AG$2:$AG$201,"CO/SO₂ simultáneos")=3,SUMIFS($J$2:$J$201,$E$2:$E$201,E2,$AH$2:$AH$201,"Confirmado",$AG$2:$AG$201,"CO/SO₂ simultáneos")=6),"Sí","No"),IF(OR(AND(F2>0,SUMIFS($F$2:$F$201,$E$2:$E$201,E2,$AH$2:$AH$201,"Confirmado")=4),AND(G2>0,SUMIFS($G$2:$G$201,$E$2:$E$201,E2,$AH$2:$AH$201,"Confirmado")=4),AND(H2>0,SUMIFS($H$2:$H$201,$E$2:$E$201,E2,$AH$2:$AH$201,"Confirmado")=4),AND(I2>0,SUMIFS($I$2:$I$201,$E$2:$E$201,E2,$AH$2:$AH$201,"Confirmado")=4)),"Sí","No")))) | AM2: =IF(A2="","",IF(AH2<>"Confirmado","",IF(AG2="CO/SO₂ simultáneos",IF(OR(COUNTIFS($E$2:$E$201,E2,$AH$2:$AH$201,"Confirmado",$AG$2:$AG$201,"CO/SO₂ simultáneos")>3,SUMIFS($J$2:$J$201,$E$2:$E$201,E2,$AH$2:$AH$201,"Confirmado",$AG$2:$AG$201,"CO/SO₂ simultáneos")>6),"CAPACIDAD EXCEDIDA","OK"),IF(OR(SUMIFS($F$2:$F$201,$E$2:$E$201,E2,$AH$2:$AH$201,"Confirmado")>4,SUMIFS($G$2:$G$201,$E$2:$E$201,E2,$AH$2:$AH$201,"Confirmado")>4,SUMIFS($H$2:$H$201,$E$2:$E$201,E2,$AH$2:$AH$201,"Confirmado")>4,SUMIFS($I$2:$I$201,$E$2:$E$201,E2,$AH$2:$AH$201,"Confirmado")>4),"CAPACIDAD EXCEDIDA","OK")))) | AN2: =IF(A2="","",IF(AND(AC2<1,Q2<TODAY(),AH2="Aceptado pendiente de pago/orden"),"PLAZO VENCIDO",IF(AND(AC2<1,AD2<>"",AD2<TODAY()),"VENCIDO","OK"))) | AR2: No aplica — solo COP | AW2: =IF(AV2="","",AV2+60) | AX2: =IF(A2="","",IF(AND(AV2<>"",AW2<TODAY(),OR(AH2="Interés",AH2="Cotizado")),"Sí","No"))
J3: =SUM(F3:I3) -> 0 | AB3: =IF(N3="","",MAX(0,N3-AA3)) | AC3: =IF(N3="","",IF(N3=0,0,AA3/N3)) | AI3: =IF(A3="","",IF(V3="Yes",IF(U3="Yes",1,2),"")) | AK3: =IF(A3="","",IF(AJ3="","",COUNTIFS($E$2:$E$201,E3,$AI$2:$AI$201,AI3,$AJ$2:$AJ$201,"<="&AJ3))) | AL3: =IF(A3="","",IF(AH3<>"Confirmado","No",IF(AG3="CO/SO₂ simultáneos",IF(OR(COUNTIFS($E$2:$E$201,E3,$AH$2:$AH$201,"Confirmado",$AG$2:$AG$201,"CO/SO₂ simultáneos")=3,SUMIFS($J$2:$J$201,$E$2:$E$201,E3,$AH$2:$AH$201,"Confirmado",$AG$2:$AG$201,"CO/SO₂ simultáneos")=6),"Sí","No"),IF(OR(AND(F3>0,SUMIFS($F$2:$F$201,$E$2:$E$201,E3,$AH$2:$AH$201,"Confirmado")=4),AND(G3>0,SUMIFS($G$2:$G$201,$E$2:$E$201,E3,$AH$2:$AH$201,"Confirmado")=4),AND(H3>0,SUMIFS($H$2:$H$201,$E$2:$E$201,E3,$AH$2:$AH$201,"Confirmado")=4),AND(I3>0,SUMIFS($I$2:$I$201,$E$2:$E$201,E3,$AH$2:$AH$201,"Confirmado")=4)),"Sí","No")))) | AM3: =IF(A3="","",IF(AH3<>"Confirmado","",IF(AG3="CO/SO₂ simultáneos",IF(OR(COUNTIFS($E$2:$E$201,E3,$AH$2:$AH$201,"Confirmado",$AG$2:$AG$201,"CO/SO₂ simultáneos")>3,SUMIFS($J$2:$J$201,$E$2:$E$201,E3,$AH$2:$AH$201,"Confirmado",$AG$2:$AG$201,"CO/SO₂ simultáneos")>6),"CAPACIDAD EXCEDIDA","OK"),IF(OR(SUMIFS($F$2:$F$201,$E$2:$E$201,E3,$AH$2:$AH$201,"Confirmado")>4,SUMIFS($G$2:$G$201,$E$2:$E$201,E3,$AH$2:$AH$201,"Confirmado")>4,SUMIFS($H$2:$H$201,$E$2:$E$201,E3,$AH$2:$AH$201,"Confirmado")>4,SUMIFS($I$2:$I$201,$E$2:$E$201,E3,$AH$2:$AH$201,"Confirmado")>4),"CAPACIDAD EXCEDIDA","OK")))) | AN3: =IF(A3="","",IF(AND(AC3<1,Q3<TODAY(),AH3="Aceptado pendiente de pago/orden"),"PLAZO VENCIDO",IF(AND(AC3<1,AD3<>"",AD3<TODAY()),"VENCIDO","OK"))) | AR3: No aplica — solo COP | AW3: =IF(AV3="","",AV3+60) | AX3: =IF(A3="","",IF(AND(AV3<>"",AW3<TODAY(),OR(AH3="Interés",AH3="Cotizado")),"Sí","No"))
J4: =SUM(F4:I4) -> 0 | AB4: =IF(N4="","",MAX(0,N4-AA4)) | AC4: =IF(N4="","",IF(N4=0,0,AA4/N4)) | AI4: =IF(A4="","",IF(V4="Yes",IF(U4="Yes",1,2),"")) | AK4: =IF(A4="","",IF(AJ4="","",COUNTIFS($E$2:$E$201,E4,$AI$2:$AI$201,AI4,$AJ$2:$AJ$201,"<="&AJ4))) | AL4: =IF(A4="","",IF(AH4<>"Confirmado","No",IF(AG4="CO/SO₂ simultáneos",IF(OR(COUNTIFS($E$2:$E$201,E4,$AH$2:$AH$201,"Confirmado",$AG$2:$AG$201,"CO/SO₂ simultáneos")=3,SUMIFS($J$2:$J$201,$E$2:$E$201,E4,$AH$2:$AH$201,"Confirmado",$AG$2:$AG$201,"CO/SO₂ simultáneos")=6),"Sí","No"),IF(OR(AND(F4>0,SUMIFS($F$2:$F$201,$E$2:$E$201,E4,$AH$2:$AH$201,"Confirmado")=4),AND(G4>0,SUMIFS($G$2:$G$201,$E$2:$E$201,E4,$AH$2:$AH$201,"Confirmado")=4),AND(H4>0,SUMIFS($H$2:$H$201,$E$2:$E$201,E4,$AH$2:$AH$201,"Confirmado")=4),AND(I4>0,SUMIFS($I$2:$I$201,$E$2:$E$201,E4,$AH$2:$AH$201,"Confirmado")=4)),"Sí","No")))) | AM4: =IF(A4="","",IF(AH4<>"Confirmado","",IF(AG4="CO/SO₂ simultáneos",IF(OR(COUNTIFS($E$2:$E$201,E4,$AH$2:$AH$201,"Confirmado",$AG$2:$AG$201,"CO/SO₂ simultáneos")>3,SUMIFS($J$2:$J$201,$E$2:$E$201,E4,$AH$2:$AH$201,"Confirmado",$AG$2:$AG$201,"CO/SO₂ simultáneos")>6),"CAPACIDAD EXCEDIDA","OK"),IF(OR(SUMIFS($F$2:$F$201,$E$2:$E$201,E4,$AH$2:$AH$201,"Confirmado")>4,SUMIFS($G$2:$G$201,$E$2:$E$201,E4,$AH$2:$AH$201,"Confirmado")>4,SUMIFS($H$2:$H$201,$E$2:$E$201,E4,$AH$2:$AH$201,"Confirmado")>4,SUMIFS($I$2:$I$201,$E$2:$E$201,E4,$AH$2:$AH$201,"Confirmado")>4),"CAPACIDAD EXCEDIDA","OK")))) | AN4: =IF(A4="","",IF(AND(AC4<1,Q4<TODAY(),AH4="Aceptado pendiente de pago/orden"),"PLAZO VENCIDO",IF(AND(AC4<1,AD4<>"",AD4<TODAY()),"VENCIDO","OK"))) | AR4: No aplica — solo COP | AW4: =IF(AV4="","",AV4+60) | AX4: =IF(A4="","",IF(AND(AV4<>"",AW4<TODAY(),OR(AH4="Interés",AH4="Cotizado")),"Sí","No"))
J5: =SUM(F5:I5) -> 0 | AB5: =IF(N5="","",MAX(0,N5-AA5)) | AC5: =IF(N5="","",IF(N5=0,0,AA5/N5)) | AI5: =IF(A5="","",IF(V5="Yes",IF(U5="Yes",1,2),"")) | AK5: =IF(A5="","",IF(AJ5="","",COUNTIFS($E$2:$E$201,E5,$AI$2:$AI$201,AI5,$AJ$2:$AJ$201,"<="&AJ5))) | AL5: =IF(A5="","",IF(AH5<>"Confirmado","No",IF(AG5="CO/SO₂ simultáneos",IF(OR(COUNTIFS($E$2:$E$201,E5,$AH$2:$AH$201,"Confirmado",$AG$2:$AG$201,"CO/SO₂ simultáneos")=3,SUMIFS($J$2:$J$201,$E$2:$E$201,E5,$AH$2:$AH$201,"Confirmado",$AG$2:$AG$201,"CO/SO₂ simultáneos")=6),"Sí","No"),IF(OR(AND(F5>0,SUMIFS($F$2:$F$201,$E$2:$E$201,E5,$AH$2:$AH$201,"Confirmado")=4),AND(G5>0,SUMIFS($G$2:$G$201,$E$2:$E$201,E5,$AH$2:$AH$201,"Confirmado")=4),AND(H5>0,SUMIFS($H$2:$H$201,$E$2:$E$201,E5,$AH$2:$AH$201,"Confirmado")=4),AND(I5>0,SUMIFS($I$2:$I$201,$E$2:$E$201,E5,$AH$2:$AH$201,"Confirmado")=4)),"Sí","No")))) | AM5: =IF(A5="","",IF(AH5<>"Confirmado","",IF(AG5="CO/SO₂ simultáneos",IF(OR(COUNTIFS($E$2:$E$201,E5,$AH$2:$AH$201,"Confirmado",$AG$2:$AG$201,"CO/SO₂ simultáneos")>3,SUMIFS($J$2:$J$201,$E$2:$E$201,E5,$AH$2:$AH$201,"Confirmado",$AG$2:$AG$201,"CO/SO₂ simultáneos")>6),"CAPACIDAD EXCEDIDA","OK"),IF(OR(SUMIFS($F$2:$F$201,$E$2:$E$201,E5,$AH$2:$AH$201,"Confirmado")>4,SUMIFS($G$2:$G$201,$E$2:$E$201,E5,$AH$2:$AH$201,"Confirmado")>4,SUMIFS($H$2:$H$201,$E$2:$E$201,E5,$AH$2:$AH$201,"Confirmado")>4,SUMIFS($I$2:$I$201,$E$2:$E$201,E5,$AH$2:$AH$201,"Confirmado")>4),"CAPACIDAD EXCEDIDA","OK")))) | AN5: =IF(A5="","",IF(AND(AC5<1,Q5<TODAY(),AH5="Aceptado pendiente de pago/orden"),"PLAZO VENCIDO",IF(AND(AC5<1,AD5<>"",AD5<TODAY()),"VENCIDO","OK"))) | AR5: No aplica — solo COP | AW5: =IF(AV5="","",AV5+60) | AX5: =IF(A5="","",IF(AND(AV5<>"",AW5<TODAY(),OR(AH5="Interés",AH5="Cotizado")),"Sí","No"))
J6: =SUM(F6:I6) -> 0 | AB6: =IF(N6="","",MAX(0,N6-AA6)) | AC6: =IF(N6="","",IF(N6=0,0,AA6/N6)) | AI6: =IF(A6="","",IF(V6="Yes",IF(U6="Yes",1,2),"")) | AK6: =IF(A6="","",IF(AJ6="","",COUNTIFS($E$2:$E$201,E6,$AI$2:$AI$201,AI6,$AJ$2:$AJ$201,"<="&AJ6))) | AL6: =IF(A6="","",IF(AH6<>"Confirmado","No",IF(AG6="CO/SO₂ simultáneos",IF(OR(COUNTIFS($E$2:$E$201,E6,$AH$2:$AH$201,"Confirmado",$AG$2:$AG$201,"CO/SO₂ simultáneos")=3,SUMIFS($J$2:$J$201,$E$2:$E$201,E6,$AH$2:$AH$201,"Confirmado",$AG$2:$AG$201,"CO/SO₂ simultáneos")=6),"Sí","No"),IF(OR(AND(F6>0,SUMIFS($F$2:$F$201,$E$2:$E$201,E6,$AH$2:$AH$201,"Confirmado")=4),AND(G6>0,SUMIFS($G$2:$G$201,$E$2:$E$201,E6,$AH$2:$AH$201,"Confirmado")=4),AND(H6>0,SUMIFS($H$2:$H$201,$E$2:$E$201,E6,$AH$2:$AH$201,"Confirmado")=4),AND(I6>0,SUMIFS($I$2:$I$201,$E$2:$E$201,E6,$AH$2:$AH$201,"Confirmado")=4)),"Sí","No")))) | AM6: =IF(A6="","",IF(AH6<>"Confirmado","",IF(AG6="CO/SO₂ simultáneos",IF(OR(COUNTIFS($E$2:$E$201,E6,$AH$2:$AH$201,"Confirmado",$AG$2:$AG$201,"CO/SO₂ simultáneos")>3,SUMIFS($J$2:$J$201,$E$2:$E$201,E6,$AH$2:$AH$201,"Confirmado",$AG$2:$AG$201,"CO/SO₂ simultáneos")>6),"CAPACIDAD EXCEDIDA","OK"),IF(OR(SUMIFS($F$2:$F$201,$E$2:$E$201,E6,$AH$2:$AH$201,"Confirmado")>4,SUMIFS($G$2:$G$201,$E$2:$E$201,E6,$AH$2:$AH$201,"Confirmado")>4,SUMIFS($H$2:$H$201,$E$2:$E$201,E6,$AH$2:$AH$201,"Confirmado")>4,SUMIFS($I$2:$I$201,$E$2:$E$201,E6,$AH$2:$AH$201,"Confirmado")>4),"CAPACIDAD EXCEDIDA","OK")))) | AN6: =IF(A6="","",IF(AND(AC6<1,Q6<TODAY(),AH6="Aceptado pendiente de pago/orden"),"PLAZO VENCIDO",IF(AND(AC6<1,AD6<>"",AD6<TODAY()),"VENCIDO","OK"))) | AR6: No aplica — solo COP | AW6: =IF(AV6="","",AV6+60) | AX6: =IF(A6="","",IF(AND(AV6<>"",AW6<TODAY(),OR(AH6="Interés",AH6="Cotizado")),"Sí","No"))
J7: =SUM(F7:I7) -> 0 | AB7: =IF(N7="","",MAX(0,N7-AA7)) | AC7: =IF(N7="","",IF(N7=0,0,AA7/N7)) | AI7: =IF(A7="","",IF(V7="Yes",IF(U7="Yes",1,2),"")) | AK7: =IF(A7="","",IF(AJ7="","",COUNTIFS($E$2:$E$201,E7,$AI$2:$AI$201,AI7,$AJ$2:$AJ$201,"<="&AJ7))) | AL7: =IF(A7="","",IF(AH7<>"Confirmado","No",IF(AG7="CO/SO₂ simultáneos",IF(OR(COUNTIFS($E$2:$E$201,E7,$AH$2:$AH$201,"Confirmado",$AG$2:$AG$201,"CO/SO₂ simultáneos")=3,SUMIFS($J$2:$J$201,$E$2:$E$201,E7,$AH$2:$AH$201,"Confirmado",$AG$2:$AG$201,"CO/SO₂ simultáneos")=6),"Sí","No"),IF(OR(AND(F7>0,SUMIFS($F$2:$F$201,$E$2:$E$201,E7,$AH$2:$AH$201,"Confirmado")=4),AND(G7>0,SUMIFS($G$2:$G$201,$E$2:$E$201,E7,$AH$2:$AH$201,"Confirmado")=4),AND(H7>0,SUMIFS($H$2:$H$201,$E$2:$E$201,E7,$AH$2:$AH$201,"Confirmado")=4),AND(I7>0,SUMIFS($I$2:$I$201,$E$2:$E$201,E7,$AH$2:$AH$201,"Confirmado")=4)),"Sí","No")))) | AM7: =IF(A7="","",IF(AH7<>"Confirmado","",IF(AG7="CO/SO₂ simultáneos",IF(OR(COUNTIFS($E$2:$E$201,E7,$AH$2:$AH$201,"Confirmado",$AG$2:$AG$201,"CO/SO₂ simultáneos")>3,SUMIFS($J$2:$J$201,$E$2:$E$201,E7,$AH$2:$AH$201,"Confirmado",$AG$2:$AG$201,"CO/SO₂ simultáneos")>6),"CAPACIDAD EXCEDIDA","OK"),IF(OR(SUMIFS($F$2:$F$201,$E$2:$E$201,E7,$AH$2:$AH$201,"Confirmado")>4,SUMIFS($G$2:$G$201,$E$2:$E$201,E7,$AH$2:$AH$201,"Confirmado")>4,SUMIFS($H$2:$H$201,$E$2:$E$201,E7,$AH$2:$AH$201,"Confirmado")>4,SUMIFS($I$2:$I$201,$E$2:$E$201,E7,$AH$2:$AH$201,"Confirmado")>4),"CAPACIDAD EXCEDIDA","OK")))) | AN7: =IF(A7="","",IF(AND(AC7<1,Q7<TODAY(),AH7="Aceptado pendiente de pago/orden"),"PLAZO VENCIDO",IF(AND(AC7<1,AD7<>"",AD7<TODAY()),"VENCIDO","OK"))) | AR7: No aplica — solo COP | AW7: =IF(AV7="","",AV7+60) | AX7: =IF(A7="","",IF(AND(AV7<>"",AW7<TODAY(),OR(AH7="Interés",AH7="Cotizado")),"Sí","No"))
J8: =SUM(F8:I8) -> 0 | AB8: =IF(N8="","",MAX(0,N8-AA8)) | AC8: =IF(N8="","",IF(N8=0,0,AA8/N8)) | AI8: =IF(A8="","",IF(V8="Yes",IF(U8="Yes",1,2),"")) | AK8: =IF(A8="","",IF(AJ8="","",COUNTIFS($E$2:$E$201,E8,$AI$2:$AI$201,AI8,$AJ$2:$AJ$201,"<="&AJ8))) | AL8: =IF(A8="","",IF(AH8<>"Confirmado","No",IF(AG8="CO/SO₂ simultáneos",IF(OR(COUNTIFS($E$2:$E$201,E8,$AH$2:$AH$201,"Confirmado",$AG$2:$AG$201,"CO/SO₂ simultáneos")=3,SUMIFS($J$2:$J$201,$E$2:$E$201,E8,$AH$2:$AH$201,"Confirmado",$AG$2:$AG$201,"CO/SO₂ simultáneos")=6),"Sí","No"),IF(OR(AND(F8>0,SUMIFS($F$2:$F$201,$E$2:$E$201,E8,$AH$2:$AH$201,"Confirmado")=4),AND(G8>0,SUMIFS($G$2:$G$201,$E$2:$E$201,E8,$AH$2:$AH$201,"Confirmado")=4),AND(H8>0,SUMIFS($H$2:$H$201,$E$2:$E$201,E8,$AH$2:$AH$201,"Confirmado")=4),AND(I8>0,SUMIFS($I$2:$I$201,$E$2:$E$201,E8,$AH$2:$AH$201,"Confirmado")=4)),"Sí","No")))) | AM8: =IF(A8="","",IF(AH8<>"Confirmado","",IF(AG8="CO/SO₂ simultáneos",IF(OR(COUNTIFS($E$2:$E$201,E8,$AH$2:$AH$201,"Confirmado",$AG$2:$AG$201,"CO/SO₂ simultáneos")>3,SUMIFS($J$2:$J$201,$E$2:$E$201,E8,$AH$2:$AH$201,"Confirmado",$AG$2:$AG$201,"CO/SO₂ simultáneos")>6),"CAPACIDAD EXCEDIDA","OK"),IF(OR(SUMIFS($F$2:$F$201,$E$2:$E$201,E8,$AH$2:$AH$201,"Confirmado")>4,SUMIFS($G$2:$G$201,$E$2:$E$201,E8,$AH$2:$AH$201,"Confirmado")>4,SUMIFS($H$2:$H$201,$E$2:$E$201,E8,$AH$2:$AH$201,"Confirmado")>4,SUMIFS($I$2:$I$201,$E$2:$E$201,E8,$AH$2:$AH$201,"Confirmado")>4),"CAPACIDAD EXCEDIDA","OK")))) | AN8: =IF(A8="","",IF(AND(AC8<1,Q8<TODAY(),AH8="Aceptado pendiente de pago/orden"),"PLAZO VENCIDO",IF(AND(AC8<1,AD8<>"",AD8<TODAY()),"VENCIDO","OK"))) | AR8: No aplica — solo COP | AW8: =IF(AV8="","",AV8+60) | AX8: =IF(A8="","",IF(AND(AV8<>"",AW8<TODAY(),OR(AH8="Interés",AH8="Cotizado")),"Sí","No"))
J9: =SUM(F9:I9) -> 0 | AB9: =IF(N9="","",MAX(0,N9-AA9)) | AC9: =IF(N9="","",IF(N9=0,0,AA9/N9)) | AI9: =IF(A9="","",IF(V9="Yes",IF(U9="Yes",1,2),"")) | AK9: =IF(A9="","",IF(AJ9="","",COUNTIFS($E$2:$E$201,E9,$AI$2:$AI$201,AI9,$AJ$2:$AJ$201,"<="&AJ9))) | AL9: =IF(A9="","",IF(AH9<>"Confirmado","No",IF(AG9="CO/SO₂ simultáneos",IF(OR(COUNTIFS($E$2:$E$201,E9,$AH$2:$AH$201,"Confirmado",$AG$2:$AG$201,"CO/SO₂ simultáneos")=3,SUMIFS($J$2:$J$201,$E$2:$E$201,E9,$AH$2:$AH$201,"Confirmado",$AG$2:$AG$201,"CO/SO₂ simultáneos")=6),"Sí","No"),IF(OR(AND(F9>0,SUMIFS($F$2:$F$201,$E$2:$E$201,E9,$AH$2:$AH$201,"Confirmado")=4),AND(G9>0,SUMIFS($G$2:$G$201,$E$2:$E$201,E9,$AH$2:$AH$201,"Confirmado")=4),AND(H9>0,SUMIFS($H$2:$H$201,$E$2:$E$201,E9,$AH$2:$AH$201,"Confirmado")=4),AND(I9>0,SUMIFS($I$2:$I$201,$E$2:$E$201,E9,$AH$2:$AH$201,"Confirmado")=4)),"Sí","No")))) | AM9: =IF(A9="","",IF(AH9<>"Confirmado","",IF(AG9="CO/SO₂ simultáneos",IF(OR(COUNTIFS($E$2:$E$201,E9,$AH$2:$AH$201,"Confirmado",$AG$2:$AG$201,"CO/SO₂ simultáneos")>3,SUMIFS($J$2:$J$201,$E$2:$E$201,E9,$AH$2:$AH$201,"Confirmado",$AG$2:$AG$201,"CO/SO₂ simultáneos")>6),"CAPACIDAD EXCEDIDA","OK"),IF(OR(SUMIFS($F$2:$F$201,$E$2:$E$201,E9,$AH$2:$AH$201,"Confirmado")>4,SUMIFS($G$2:$G$201,$E$2:$E$201,E9,$AH$2:$AH$201,"Confirmado")>4,SUMIFS($H$2:$H$201,$E$2:$E$201,E9,$AH$2:$AH$201,"Confirmado")>4,SUMIFS($I$2:$I$201,$E$2:$E$201,E9,$AH$2:$AH$201,"Confirmado")>4),"CAPACIDAD EXCEDIDA","OK")))) | AN9: =IF(A9="","",IF(AND(AC9<1,Q9<TODAY(),AH9="Aceptado pendiente de pago/orden"),"PLAZO VENCIDO",IF(AND(AC9<1,AD9<>"",AD9<TODAY()),"VENCIDO","OK"))) | AR9: No aplica — solo COP | AW9: =IF(AV9="","",AV9+60) | AX9: =IF(A9="","",IF(AND(AV9<>"",AW9<TODAY(),OR(AH9="Interés",AH9="Cotizado")),"Sí","No"))
J10: =SUM(F10:I10) -> 0 | AB10: =IF(N10="","",MAX(0,N10-AA10)) | AC10: =IF(N10="","",IF(N10=0,0,AA10/N10)) | AI10: =IF(A10="","",IF(V10="Yes",IF(U10="Yes",1,2),"")) | AK10: =IF(A10="","",IF(AJ10="","",COUNTIFS($E$2:$E$201,E10,$AI$2:$AI$201,AI10,$AJ$2:$AJ$201,"<="&AJ10))) | AL10: =IF(A10="","",IF(AH10<>"Confirmado","No",IF(AG10="CO/SO₂ simultáneos",IF(OR(COUNTIFS($E$2:$E$201,E10,$AH$2:$AH$201,"Confirmado",$AG$2:$AG$201,"CO/SO₂ simultáneos")=3,SUMIFS($J$2:$J$201,$E$2:$E$201,E10,$AH$2:$AH$201,"Confirmado",$AG$2:$AG$201,"CO/SO₂ simultáneos")=6),"Sí","No"),IF(OR(AND(F10>0,SUMIFS($F$2:$F$201,$E$2:$E$201,E10,$AH$2:$AH$201,"Confirmado")=4),AND(G10>0,SUMIFS($G$2:$G$201,$E$2:$E$201,E10,$AH$2:$AH$201,"Confirmado")=4),AND(H10>0,SUMIFS($H$2:$H$201,$E$2:$E$201,E10,$AH$2:$AH$201,"Confirmado")=4),AND(I10>0,SUMIFS($I$2:$I$201,$E$2:$E$201,E10,$AH$2:$AH$201,"Confirmado")=4)),"Sí","No")))) | AM10: =IF(A10="","",IF(AH10<>"Confirmado","",IF(AG10="CO/SO₂ simultáneos",IF(OR(COUNTIFS($E$2:$E$201,E10,$AH$2:$AH$201,"Confirmado",$AG$2:$AG$201,"CO/SO₂ simultáneos")>3,SUMIFS($J$2:$J$201,$E$2:$E$201,E10,$AH$2:$AH$201,"Confirmado",$AG$2:$AG$201,"CO/SO₂ simultáneos")>6),"CAPACIDAD EXCEDIDA","OK"),IF(OR(SUMIFS($F$2:$F$201,$E$2:$E$201,E10,$AH$2:$AH$201,"Confirmado")>4,SUMIFS($G$2:$G$201,$E$2:$E$201,E10,$AH$2:$AH$201,"Confirmado")>4,SUMIFS($H$2:$H$201,$E$2:$E$201,E10,$AH$2:$AH$201,"Confirmado")>4,SUMIFS($I$2:$I$201,$E$2:$E$201,E10,$AH$2:$AH$201,"Confirmado")>4),"CAPACIDAD EXCEDIDA","OK")))) | AN10: =IF(A10="","",IF(AND(AC10<1,Q10<TODAY(),AH10="Aceptado pendiente de pago/orden"),"PLAZO VENCIDO",IF(AND(AC10<1,AD10<>"",AD10<TODAY()),"VENCIDO","OK"))) | AR10: No aplica — solo COP | AW10: =IF(AV10="","",AV10+60) | AX10: =IF(A10="","",IF(AND(AV10<>"",AW10<TODAY(),OR(AH10="Interés",AH10="Cotizado")),"Sí","No"))
J11: =SUM(F11:I11) -> 0 | AB11: =IF(N11="","",MAX(0,N11-AA11)) | AC11: =IF(N11="","",IF(N11=0,0,AA11/N11)) | AI11: =IF(A11="","",IF(V11="Yes",IF(U11="Yes",1,2),"")) | AK11: =IF(A11="","",IF(AJ11="","",COUNTIFS($E$2:$E$201,E11,$AI$2:$AI$201,AI11,$AJ$2:$AJ$201,"<="&AJ11))) | AL11: =IF(A11="","",IF(AH11<>"Confirmado","No",IF(AG11="CO/SO₂ simultáneos",IF(OR(COUNTIFS($E$2:$E$201,E11,$AH$2:$AH$201,"Confirmado",$AG$2:$AG$201,"CO/SO₂ simultáneos")=3,SUMIFS($J$2:$J$201,$E$2:$E$201,E11,$AH$2:$AH$201,"Confirmado",$AG$2:$AG$201,"CO/SO₂ simultáneos")=6),"Sí","No"),IF(OR(AND(F11>0,SUMIFS($F$2:$F$201,$E$2:$E$201,E11,$AH$2:$AH$201,"Confirmado")=4),AND(G11>0,SUMIFS($G$2:$G$201,$E$2:$E$201,E11,$AH$2:$AH$201,"Confirmado")=4),AND(H11>0,SUMIFS($H$2:$H$201,$E$2:$E$201,E11,$AH$2:$AH$201,"Confirmado")=4),AND(I11>0,SUMIFS($I$2:$I$201,$E$2:$E$201,E11,$AH$2:$AH$201,"Confirmado")=4)),"Sí","No")))) | AM11: =IF(A11="","",IF(AH11<>"Confirmado","",IF(AG11="CO/SO₂ simultáneos",IF(OR(COUNTIFS($E$2:$E$201,E11,$AH$2:$AH$201,"Confirmado",$AG$2:$AG$201,"CO/SO₂ simultáneos")>3,SUMIFS($J$2:$J$201,$E$2:$E$201,E11,$AH$2:$AH$201,"Confirmado",$AG$2:$AG$201,"CO/SO₂ simultáneos")>6),"CAPACIDAD EXCEDIDA","OK"),IF(OR(SUMIFS($F$2:$F$201,$E$2:$E$201,E11,$AH$2:$AH$201,"Confirmado")>4,SUMIFS($G$2:$G$201,$E$2:$E$201,E11,$AH$2:$AH$201,"Confirmado")>4,SUMIFS($H$2:$H$201,$E$2:$E$201,E11,$AH$2:$AH$201,"Confirmado")>4,SUMIFS($I$2:$I$201,$E$2:$E$201,E11,$AH$2:$AH$201,"Confirmado")>4),"CAPACIDAD EXCEDIDA","OK")))) | AN11: =IF(A11="","",IF(AND(AC11<1,Q11<TODAY(),AH11="Aceptado pendiente de pago/orden"),"PLAZO VENCIDO",IF(AND(AC11<1,AD11<>"",AD11<TODAY()),"VENCIDO","OK"))) | AR11: No aplica — solo COP | AW11: =IF(AV11="","",AV11+60) | AX11: =IF(A11="","",IF(AND(AV11<>"",AW11<TODAY(),OR(AH11="Interés",AH11="Cotizado")),"Sí","No"))
J12: =SUM(F12:I12) -> 0 | AB12: =IF(N12="","",MAX(0,N12-AA12)) | AC12: =IF(N12="","",IF(N12=0,0,AA12/N12)) | AI12: =IF(A12="","",IF(V12="Yes",IF(U12="Yes",1,2),"")) | AK12: =IF(A12="","",IF(AJ12="","",COUNTIFS($E$2:$E$201,E12,$AI$2:$AI$201,AI12,$AJ$2:$AJ$201,"<="&AJ12))) | AL12: =IF(A12="","",IF(AH12<>"Confirmado","No",IF(AG12="CO/SO₂ simultáneos",IF(OR(COUNTIFS($E$2:$E$201,E12,$AH$2:$AH$201,"Confirmado",$AG$2:$AG$201,"CO/SO₂ simultáneos")=3,SUMIFS($J$2:$J$201,$E$2:$E$201,E12,$AH$2:$AH$201,"Confirmado",$AG$2:$AG$201,"CO/SO₂ simultáneos")=6),"Sí","No"),IF(OR(AND(F12>0,SUMIFS($F$2:$F$201,$E$2:$E$201,E12,$AH$2:$AH$201,"Confirmado")=4),AND(G12>0,SUMIFS($G$2:$G$201,$E$2:$E$201,E12,$AH$2:$AH$201,"Confirmado")=4),AND(H12>0,SUMIFS($H$2:$H$201,$E$2:$E$201,E12,$AH$2:$AH$201,"Confirmado")=4),AND(I12>0,SUMIFS($I$2:$I$201,$E$2:$E$201,E12,$AH$2:$AH$201,"Confirmado")=4)),"Sí","No")))) | AM12: =IF(A12="","",IF(AH12<>"Confirmado","",IF(AG12="CO/SO₂ simultáneos",IF(OR(COUNTIFS($E$2:$E$201,E12,$AH$2:$AH$201,"Confirmado",$AG$2:$AG$201,"CO/SO₂ simultáneos")>3,SUMIFS($J$2:$J$201,$E$2:$E$201,E12,$AH$2:$AH$201,"Confirmado",$AG$2:$AG$201,"CO/SO₂ simultáneos")>6),"CAPACIDAD EXCEDIDA","OK"),IF(OR(SUMIFS($F$2:$F$201,$E$2:$E$201,E12,$AH$2:$AH$201,"Confirmado")>4,SUMIFS($G$2:$G$201,$E$2:$E$201,E12,$AH$2:$AH$201,"Confirmado")>4,SUMIFS($H$2:$H$201,$E$2:$E$201,E12,$AH$2:$AH$201,"Confirmado")>4,SUMIFS($I$2:$I$201,$E$2:$E$201,E12,$AH$2:$AH$201,"Confirmado")>4),"CAPACIDAD EXCEDIDA","OK")))) | AN12: =IF(A12="","",IF(AND(AC12<1,Q12<TODAY(),AH12="Aceptado pendiente de pago/orden"),"PLAZO VENCIDO",IF(AND(AC12<1,AD12<>"",AD12<TODAY()),"VENCIDO","OK"))) | AR12: No aplica — solo COP | AW12: =IF(AV12="","",AV12+60) | AX12: =IF(A12="","",IF(AND(AV12<>"",AW12<TODAY(),OR(AH12="Interés",AH12="Cotizado")),"Sí","No"))
J13: =SUM(F13:I13) -> 0 | AB13: =IF(N13="","",MAX(0,N13-AA13)) | AC13: =IF(N13="","",IF(N13=0,0,AA13/N13)) | AI13: =IF(A13="","",IF(V13="Yes",IF(U13="Yes",1,2),"")) | AK13: =IF(A13="","",IF(AJ13="","",COUNTIFS($E$2:$E$201,E13,$AI$2:$AI$201,AI13,$AJ$2:$AJ$201,"<="&AJ13))) | AL13: =IF(A13="","",IF(AH13<>"Confirmado","No",IF(AG13="CO/SO₂ simultáneos",IF(OR(COUNTIFS($E$2:$E$201,E13,$AH$2:$AH$201,"Confirmado",$AG$2:$AG$201,"CO/SO₂ simultáneos")=3,SUMIFS($J$2:$J$201,$E$2:$E$201,E13,$AH$2:$AH$201,"Confirmado",$AG$2:$AG$201,"CO/SO₂ simultáneos")=6),"Sí","No"),IF(OR(AND(F13>0,SUMIFS($F$2:$F$201,$E$2:$E$201,E13,$AH$2:$AH$201,"Confirmado")=4),AND(G13>0,SUMIFS($G$2:$G$201,$E$2:$E$201,E13,$AH$2:$AH$201,"Confirmado")=4),AND(H13>0,SUMIFS($H$2:$H$201,$E$2:$E$201,E13,$AH$2:$AH$201,"Confirmado")=4),AND(I13>0,SUMIFS($I$2:$I$201,$E$2:$E$201,E13,$AH$2:$AH$201,"Confirmado")=4)),"Sí","No")))) | AM13: =IF(A13="","",IF(AH13<>"Confirmado","",IF(AG13="CO/SO₂ simultáneos",IF(OR(COUNTIFS($E$2:$E$201,E13,$AH$2:$AH$201,"Confirmado",$AG$2:$AG$201,"CO/SO₂ simultáneos")>3,SUMIFS($J$2:$J$201,$E$2:$E$201,E13,$AH$2:$AH$201,"Confirmado",$AG$2:$AG$201,"CO/SO₂ simultáneos")>6),"CAPACIDAD EXCEDIDA","OK"),IF(OR(SUMIFS($F$2:$F$201,$E$2:$E$201,E13,$AH$2:$AH$201,"Confirmado")>4,SUMIFS($G$2:$G$201,$E$2:$E$201,E13,$AH$2:$AH$201,"Confirmado")>4,SUMIFS($H$2:$H$201,$E$2:$E$201,E13,$AH$2:$AH$201,"Confirmado")>4,SUMIFS($I$2:$I$201,$E$2:$E$201,E13,$AH$2:$AH$201,"Confirmado")>4),"CAPACIDAD EXCEDIDA","OK")))) | AN13: =IF(A13="","",IF(AND(AC13<1,Q13<TODAY(),AH13="Aceptado pendiente de pago/orden"),"PLAZO VENCIDO",IF(AND(AC13<1,AD13<>"",AD13<TODAY()),"VENCIDO","OK"))) | AR13: No aplica — solo COP | AW13: =IF(AV13="","",AV13+60) | AX13: =IF(A13="","",IF(AND(AV13<>"",AW13<TODAY(),OR(AH13="Interés",AH13="Cotizado")),"Sí","No"))
... J201: =SUM(F201:I201) -> 0 | AB201: =IF(N201="","",MAX(0,N201-AA201)) | AC201: =IF(N201="","",IF(N201=0,0,AA201/N201)) | AI201: =IF(A201="","",IF(V201="Yes",IF(U201="Yes",1,2),"")) | AK201: =IF(A201="","",IF(AJ201="","",COUNTIFS($E$2:$E$201,E201,$AI$2:$AI$201,AI201,$AJ$2:$AJ$201,"<="&AJ201))) | AL201: =IF(A201="","",IF(AH201<>"Confirmado","No",IF(AG201="CO/SO₂ simultáneos",IF(OR(COUNTIFS($E$2:$E$201,E201,$AH$2:$AH$201,"Confirmado",$AG$2:$AG$201,"CO/SO₂ simultáneos")=3,SUMIFS($J$2:$J$201,$E$2:$E$201,E201,$AH$2:$AH$201,"Confirmado",$AG$2:$AG$201,"CO/SO₂ simultáneos")=6),"Sí","No"),IF(OR(AND(F201>0,SUMIFS($F$2:$F$201,$E$2:$E$201,E201,$AH$2:$AH$201,"Confirmado")=4),AND(G201>0,SUMIFS($G$2:$G$201,$E$2:$E$201,E201,$AH$2:$AH$201,"Confirmado")=4),AND(H201>0,SUMIFS($H$2:$H$201,$E$2:$E$201,E201,$AH$2:$AH$201,"Confirmado")=4),AND(I201>0,SUMIFS($I$2:$I$201,$E$2:$E$201,E201,$AH$2:$AH$201,"Confirmado")=4)),"Sí","No")))) | AM201: =IF(A201="","",IF(AH201<>"Confirmado","",IF(AG201="CO/SO₂ simultáneos",IF(OR(COUNTIFS($E$2:$E$201,E201,$AH$2:$AH$201,"Confirmado",$AG$2:$AG$201,"CO/SO₂ simultáneos")>3,SUMIFS($J$2:$J$201,$E$2:$E$201,E201,$AH$2:$AH$201,"Confirmado",$AG$2:$AG$201,"CO/SO₂ simultáneos")>6),"CAPACIDAD EXCEDIDA","OK"),IF(OR(SUMIFS($F$2:$F$201,$E$2:$E$201,E201,$AH$2:$AH$201,"Confirmado")>4,SUMIFS($G$2:$G$201,$E$2:$E$201,E201,$AH$2:$AH$201,"Confirmado")>4,SUMIFS($H$2:$H$201,$E$2:$E$201,E201,$AH$2:$AH$201,"Confirmado")>4,SUMIFS($I$2:$I$201,$E$2:$E$201,E201,$AH$2:$AH$201,"Confirmado")>4),"CAPACIDAD EXCEDIDA","OK")))) | AN201: =IF(A201="","",IF(AND(AC201<1,Q201<TODAY(),AH201="Aceptado pendiente de pago/orden"),"PLAZO VENCIDO",IF(AND(AC201<1,AD201<>"",AD201<TODAY()),"VENCIDO","OK"))) | AR201: No aplica — solo COP | AW201: =IF(AV201="","",AV201+60) | AX201: =IF(A201="","",IF(AND(AV201<>"",AW201<TODAY(),OR(AH201="Interés",AH201="Cotizado")),"Sí","No"))

Sheet Pipeline
A1: Flujo de oportunidades
A2: Interés hasta cotización; excluye intereses obsoletos.
A4: Intereses activos | B4: =COUNTIFS(Tracker!AH2:AH201,"Interés",Tracker!AX2:AX201,"No") -> 0
A5: Cotizaciones activas | B5: =COUNTIFS(Tracker!AH2:AH201,"Cotizado",Tracker!AX2:AX201,"No") -> 0
A6: Revisiones de cotización en curso | B6: =COUNTIF(Tracker!AH2:AH201,"Revisión de cotización en curso") -> 0
A7: Intereses obsoletos | B7: =COUNTIF(Tracker!AX2:AX201,"Sí") -> 0

Sheet Enrollment
A1: Inscripción
A2: Capacidad confirmada para la ronda indicada en B3.
A3: ID de ronda
A5: Indicador | B5: Confirmado | C5: Límite | D5: Residual | E5: Alerta
A6: Analizadores de CO | B6: =SUMIFS(Tracker!F2:F201,Tracker!E2:E201,$B$3,Tracker!AH2:AH201,"Confirmed") -> 0 | C6: 4 | D6: =C6-B6 -> 4 | E6: =IF(D6<0,"OVER CAPACITY",IF(D6=0,"LAST SLOT","OK")) -> OK
A7: Analizadores de SO₂ | B7: =SUMIFS(Tracker!G2:G201,Tracker!E2:E201,$B$3,Tracker!AH2:AH201,"Confirmed") -> 0 | C7: 4 | D7: =C7-B7 -> 4 | E7: =IF(D7<0,"OVER CAPACITY",IF(D7=0,"LAST SLOT","OK")) -> OK
A8: Analizadores de O₃ | B8: =SUMIFS(Tracker!H2:H201,Tracker!E2:E201,$B$3,Tracker!AH2:AH201,"Confirmed") -> 0 | C8: 4 | D8: =C8-B8 -> 4 | E8: =IF(D8<0,"OVER CAPACITY",IF(D8=0,"LAST SLOT","OK")) -> OK
A9: Analizadores de NO/NO₂ | B9: =SUMIFS(Tracker!I2:I201,Tracker!E2:E201,$B$3,Tracker!AH2:AH201,"Confirmed") -> 0 | C9: 4 | D9: =C9-B9 -> 4 | E9: =IF(D9<0,"OVER CAPACITY",IF(D9=0,"LAST SLOT","OK")) -> OK
A11: Organizaciones con CO/SO₂ simultáneos | B11: =COUNTIFS(Tracker!E2:E201,$B$3,Tracker!AH2:AH201,"Confirmed",Tracker!AG2:AG201,"Simultaneous CO/SO₂") -> 0 | C11: 3 | D11: =C11-B11 -> 3 | E11: =IF(D11<0,"OVER CAPACITY",IF(D11=0,"LAST SLOT","OK")) -> OK
A12: Analizadores de CO/SO₂ simultáneos | B12: =SUMIFS(Tracker!J2:J201,Tracker!E2:E201,$B$3,Tracker!AH2:AH201,"Confirmed",Tracker!AG2:AG201,"Simultaneous CO/SO₂") -> 0 | C12: 6 | D12: =C12-B12 -> 6 | E12: =IF(D12<0,"OVER CAPACITY",IF(D12=0,"LAST SLOT","OK")) -> OK

Sheet Viability
A1: Viabilidad
A2: Ingresos confirmados frente al umbral. Indique la ronda y el umbral aprobado en CS-04.
A3: ID de ronda
A4: Ingreso mínimo aprobado (COP)
A5: Organizaciones confirmadas | B5: =COUNTIFS(Tracker!E2:E201,B3,Tracker!AH2:AH201,"Confirmado") -> 0
A6: Ingreso comprometido confirmado (COP) | B6: =SUMIFS(Tracker!N2:N201,Tracker!E2:E201,B3,Tracker!AH2:AH201,"Confirmado") -> 0
A7: Brecha/superávit (COP) | B7: =B6-B4 -> 0
A8: Decisión | B8: =IF(B4="","PENDIENTE CS-04",IF(B6>=B4,"CUMPLE EL UMBRAL","POR DEBAJO DEL UMBRAL")) -> PENDIENTE CS-04

Sheet Receivables
A1: Cuentas por cobrar
A2: Resumen de caja y vencimientos de los registros del rastreador.
A4: Committed COP | B4: =SUM(Tracker!N2:N201) -> 0
A5: Received COP | B5: =SUM(Tracker!AA2:AA201) -> 0
A6: Outstanding COP | B6: =SUM(Tracker!AB2:AB201) -> 0
A7: Overdue accounts | B7: =COUNTIF(Tracker!AN2:AN201,"OVERDUE") -> 0
A8: Expired payment/PO deadlines | B8: =COUNTIF(Tracker!AN2:AN201,"DEADLINE EXPIRED") -> 0

Sheet Exceptions
A1: Excepciones
A2: Registros en lista de espera, rechazados, retirados, cancelados, reembolsados o en disputa.
A4: Wait-listed | B4: =COUNTIF(Tracker!AH2:AH201,"Wait-listed") -> 0
A5: Rejected | B5: =COUNTIF(Tracker!AH2:AH201,"Rejected") -> 0
A6: Withdrawn | B6: =COUNTIF(Tracker!AH2:AH201,"Withdrawn") -> 0
A7: Cancelled | B7: =COUNTIF(Tracker!AO2:AO201,"Cancelled") -> 0
A8: Refunded | B8: =COUNTIF(Tracker!AO2:AO201,"Refunded") -> 0
A9: Disputed | B9: =COUNTIF(Tracker!AO2:AO201,"Disputed") -> 0

Sheet Lists
A1: Los valores controlados están incorporados en las validaciones del rastreador. Esta hoja se reserva para ampliaciones institucionales.
